avassa_client/__init__.py
avassa_client/volga.py
avassa_client-2025.7.1.dist-info/licenses/LICENSE
avassa_client-2025.7.1.dist-info/METADATA
avassa_client-2025.7.1.dist-info/WHEEL
avassa_client-2025.7.1.dist-info/top_level.txt
avassa_client-2025.7.1.dist-info/RECORD
