Metadata-Version: 2.4
Name: avassa-client
Version: 2025.7.1
Summary: Library for integrating with the Avassa APIs
Author-email: Avassa <info@avassa.io>
License:                                  Apache License
Project-URL: Homepage, https://gitlab.com/avassa-public/avassa-client-py
Keywords: edge,avassa
Classifier: License :: OSI Approved :: Apache Software License
Classifier: Programming Language :: Python
Classifier: Programming Language :: Python :: 3
Requires-Python: >=3.9
License-File: LICENSE
Requires-Dist: websockets>=11
Dynamic: license-file
